apiprompting/__init__.py
apiprompting/api_clip/clip_prs/.gitignore
apiprompting/api_clip/clip_prs/LICENSE.txt
apiprompting/api_clip/clip_prs/README.md
apiprompting/api_clip/clip_prs/environment.yml
apiprompting/api_clip/clip_prs/utils/__init__.py
apiprompting/api_clip/clip_prs/utils/binary_waterbirds.py
apiprompting/api_clip/clip_prs/utils/constants.py
apiprompting/api_clip/clip_prs/utils/cub_classes.py
apiprompting/api_clip/clip_prs/utils/factory.py
apiprompting/api_clip/clip_prs/utils/hook.py
apiprompting/api_clip/clip_prs/utils/imagenet_classes.py
apiprompting/api_clip/clip_prs/utils/imagenet_segmentation.py
apiprompting/api_clip/clip_prs/utils/misc.py
apiprompting/api_clip/clip_prs/utils/model.py
apiprompting/api_clip/clip_prs/utils/model_configs/EVA01-g-14-plus.json
apiprompting/api_clip/clip_prs/utils/model_configs/EVA01-g-14.json
apiprompting/api_clip/clip_prs/utils/model_configs/EVA02-B-16.json
apiprompting/api_clip/clip_prs/utils/model_configs/EVA02-E-14-plus.json
apiprompting/api_clip/clip_prs/utils/model_configs/EVA02-E-14.json
apiprompting/api_clip/clip_prs/utils/model_configs/EVA02-L-14-336.json
apiprompting/api_clip/clip_prs/utils/model_configs/EVA02-L-14.json
apiprompting/api_clip/clip_prs/utils/model_configs/ViT-B-16-plus-240.json
apiprompting/api_clip/clip_prs/utils/model_configs/ViT-B-16-plus.json
apiprompting/api_clip/clip_prs/utils/model_configs/ViT-B-16.json
apiprompting/api_clip/clip_prs/utils/model_configs/ViT-B-32-plus-256.json
apiprompting/api_clip/clip_prs/utils/model_configs/ViT-B-32-quickgelu.json
apiprompting/api_clip/clip_prs/utils/model_configs/ViT-B-32.json
apiprompting/api_clip/clip_prs/utils/model_configs/ViT-H-14.json
apiprompting/api_clip/clip_prs/utils/model_configs/ViT-H-16.json
apiprompting/api_clip/clip_prs/utils/model_configs/ViT-L-14-280.json
apiprompting/api_clip/clip_prs/utils/model_configs/ViT-L-14-336.json
apiprompting/api_clip/clip_prs/utils/model_configs/ViT-L-14.json
apiprompting-0.1.0rc2.dist-info/LICENSE
apiprompting-0.1.0rc2.dist-info/METADATA
apiprompting-0.1.0rc2.dist-info/WHEEL
apiprompting-0.1.0rc2.dist-info/RECORD
