Metadata-Version: 2.1
Name: apiprompting
Version: 0.1.0rc2
Summary: Package for an easy implementation of paper "Attention Prompting on Image for Large Vision-Language Models".
License: MIT
Author: runpeng yu
Requires-Python: >=3.10,<4.0
Classifier: License :: OSI Approved :: MIT License
Classifier: Programming Language :: Python :: 3
Classifier: Programming Language :: Python :: 3.10
Classifier: Programming Language :: Python :: 3.11
Classifier: Programming Language :: Python :: 3.12
Requires-Dist: accelerate (==0.21.0)
Requires-Dist: apillava (==0.1.0)
Requires-Dist: bitsandbytes (==0.41.0)
Requires-Dist: einops (==0.6.1)
Requires-Dist: einops-exts (==0.0.4)
Requires-Dist: fastapi (>=0.112.2,<0.113.0)
Requires-Dist: ftfy (==6.2.3)
Requires-Dist: gradio (==3.35.2)
Requires-Dist: gradio_client (==0.2.9)
Requires-Dist: h5py (==3.11.0)
Requires-Dist: httpx (==0.24.0)
Requires-Dist: imageio (==2.35.1)
Requires-Dist: markdown2[all] (>=2.5.0,<3.0.0)
Requires-Dist: numpy (==1.24.0)
Requires-Dist: opencv-python (==4.10.0.84)
Requires-Dist: peft (==0.4.0)
Requires-Dist: pydantic (>=1,<2)
Requires-Dist: regex (==2024.7.24)
Requires-Dist: requests (>=2.32.3,<3.0.0)
Requires-Dist: scikit-image (==0.24.0)
Requires-Dist: scikit-learn (==1.2.2)
Requires-Dist: scipy (==1.14.1)
Requires-Dist: sentencepiece (==0.1.99)
Requires-Dist: shortuuid (==1.0.13)
Requires-Dist: timm (==0.6.13)
Requires-Dist: tokenizers (>=0.12.1,<0.14)
Requires-Dist: torch (==2.0.1)
Requires-Dist: torchvision (==0.15.2)
Requires-Dist: transformers (==4.31.0)
Requires-Dist: uvicorn (>=0.30.6,<0.31.0)
